zalando_kubectl/__init__.py
zalando_kubectl/__main__.py
zalando_kubectl/access_request.py
zalando_kubectl/completion.py
zalando_kubectl/generate.py
zalando_kubectl/kube_config.py
zalando_kubectl/kube_permissions.py
zalando_kubectl/main.py
zalando_kubectl/priv_api.py
zalando_kubectl/registry.py
zalando_kubectl/secrets.py
zalando_kubectl/templating.py
zalando_kubectl/traffic.py
zalando_kubectl/utils.py
zalando_kubectl/models/__init__.py
zalando_kubectl/models/bluegreen.py
zalando_kubectl/models/deployment.py
zalando_kubectl/models/stack.py
zalando_kubectl/models/stackset.py
zalando_kubectl/models/stackset_ingress_authoritative.py
zalando_kubectl/templates/senza/NOTES.txt
zalando_kubectl/templates/senza/delivery.yaml
zalando_kubectl/templates/senza/deploy/apply/credentials.yaml
zalando_kubectl/templates/senza/deploy/apply/deployment.yaml
zalando_kubectl/templates/senza/deploy/apply/ingress.yaml
zalando_kubectl/templates/senza/deploy/apply/service.yaml
zalando_kubectl/templates/traffic/NOTES.txt
zalando_kubectl/templates/traffic/delivery.yaml
zalando_kubectl/templates/traffic/deploy/apply/stackset.yaml
zalando_kubectl/templates/webapp/NOTES.txt
zalando_kubectl/templates/webapp/delivery.yaml
zalando_kubectl/templates/webapp/deploy/apply/deployment.yaml
zalando_kubectl/templates/webapp/deploy/apply/ingress.yaml
zalando_kubectl/templates/webapp/deploy/apply/service.yaml
zalando_kubectl/templates/webapp_appdynamics/NOTES.txt
zalando_kubectl/templates/webapp_appdynamics/delivery.yaml
zalando_kubectl/templates/webapp_appdynamics/deploy/apply/deployment.yaml
zalando_kubectl/templates/webapp_appdynamics/deploy/apply/ingress.yaml
zalando_kubectl/templates/webapp_appdynamics/deploy/apply/service.yaml
zalando_kubectl-1.33.4.372.dist-info/licenses/LICENSE
zalando_kubectl-1.33.4.372.dist-info/METADATA
zalando_kubectl-1.33.4.372.dist-info/WHEEL
zalando_kubectl-1.33.4.372.dist-info/entry_points.txt
zalando_kubectl-1.33.4.372.dist-info/top_level.txt
zalando_kubectl-1.33.4.372.dist-info/RECORD
