Metadata-Version: 2.4
Name: zalando-kubectl
Version: 1.33.4.372
Summary: Kubectl wrapper in Python with OAuth token auth
Author-email: Zalando Cloud Platform <cloud-platform@zalando.de>
License-Expression: Apache-2.0
Project-URL: Homepage, https://github.com/zalando-build/zalando-kubectl
Requires-Python: >=3.11
License-File: LICENSE
Requires-Dist: pyjwt<3.0,>=2.0
Requires-Dist: pyyaml>=3.11
Requires-Dist: click>=7.0.0
Requires-Dist: jinja2<4.0.0,>=3.1.6
Requires-Dist: natsort>=6.0.0
Requires-Dist: python-dateutil<3.0.0,>=2.9.0.post0
Requires-Dist: rich<14,>=12.6.0
Requires-Dist: setuptools<72.0.0,>=30
Requires-Dist: humanize<5.0.0,>=4.13.0
Requires-Dist: requests[security]<3.0.0,>=2.32.5
Requires-Dist: stups-tokens>=1.1.19
Requires-Dist: clickclick>=20.10.2
Requires-Dist: stups-cli-support>=1.1.22
Requires-Dist: stups-zign>=1.2
Dynamic: license-file
